README.md
setup.cfg
setup.py
sprinklerspi/__init__.py
sprinklerspi/main.py
sprinklerspi/tools.py
sprinklerspi_api.egg-info/PKG-INFO
sprinklerspi_api.egg-info/SOURCES.txt
sprinklerspi_api.egg-info/dependency_links.txt
sprinklerspi_api.egg-info/requires.txt
sprinklerspi_api.egg-info/top_level.txt