Metadata-Version: 2.1
Name: sprinklerspi-api
Version: 0.0.3
Summary: Python library to interface with Sprinkler PI
Home-page: https://github.com/a-reda/sprinklerspi-api
Author: Reda
Author-email: reda@aissaoui.org
License: UNKNOWN
Platform: UNKNOWN
Classifier: Programming Language :: Python :: 3
Classifier: License :: OSI Approved :: MIT License
Classifier: Operating System :: OS Independent
